bela/__init__.py
bela/conf/__init__.py
bela/conf/config.py
bela/conf/joint_el.yaml
bela/conf/joint_el_aida.yaml
bela/conf/joint_el_disambiguation_large.yaml
bela/conf/joint_el_disambiguation_mel.yaml
bela/conf/joint_el_disambiguation_mel_new.yaml
bela/conf/joint_el_disambiguation_only.yaml
bela/conf/joint_el_eval.yaml
bela/conf/joint_el_mel.yaml
bela/conf/joint_el_mel_new.yaml
bela/conf/joint_el_mel_new_aida.yaml
bela/conf/joint_el_mel_new_index.yaml
bela/conf/joint_el_mel_new_index_debug_mention_detection.yaml
bela/conf/joint_el_mel_new_index_tackbp.yaml
bela/conf/joint_el_mel_new_mewsli.yaml
bela/conf/checkpoint_callback/default.yaml
bela/conf/datamodule/joint_el_datamodule.yaml
bela/conf/task/joint_el_task.yaml
bela/conf/task/model/bert.yaml
bela/conf/task/model/xlmr.yaml
bela/conf/task/model/xlmr_large.yaml
bela/conf/task/optim/adamw.yaml
bela/conf/task/transform/joint_el_bert_transform.yaml
bela/conf/task/transform/joint_el_xlmr_raw_transform_large.yaml
bela/conf/task/transform/joint_el_xlmr_transform.yaml
bela/conf/task/transform/joint_el_xlmr_transform_large.yaml
bela/conf/trainer/cpu.yaml
bela/conf/trainer/gpu_1_host.yaml
bela/conf/trainer/slurm.yaml
bela/data/__init__.py
bela/data/sp_model
bela/data/vocab
bela/datamodule/__init__.py
bela/datamodule/joint_el_datamodule.py
bela/evaluation/model_eval.py
bela/models/__init__.py
bela/models/hf_encoder.py
bela/task/__init__.py
bela/task/joint_el_task.py
bela/tests/__init__.py
bela/tests/test_datamodules.py
bela/tests/test_models.py
bela/tests/test_transforms.py
bela/tests/data/el_catalogue.idx
bela/tests/data/el_matcha_joint.jsonl
bela/transforms/__init__.py
bela/transforms/hf_transform.py
bela/transforms/joint_el_transform.py
bela/transforms/sentencepiece_pb2.py
bela/transforms/spm_transform.py
bela/utils/__init__.py
bela/utils/analysis_utils.py
bela/utils/prediction_utils.py
bela/utils/utils.py
multiel/__init__.py
multiel/bela_model.py
MultiEL-0.5.dist-info/LICENSE
MultiEL-0.5.dist-info/METADATA
MultiEL-0.5.dist-info/WHEEL
MultiEL-0.5.dist-info/top_level.txt
MultiEL-0.5.dist-info/RECORD
